LICENSE
MANIFEST.in
README.md
setup.py
rip_counter/__init__.py
rip_counter/_version.py
rip_counter/scrap.py
rip_counter/scraper.py
rip_counter/scraper_utils.py
rip_counter.egg-info/PKG-INFO
rip_counter.egg-info/SOURCES.txt
rip_counter.egg-info/dependency_links.txt
rip_counter.egg-info/entry_points.txt
rip_counter.egg-info/top_level.txt
rip_counter/bot/__init__.py
rip_counter/bot/bot.py
rip_counter/bot/utils.py
rip_counter/captcha_solver/__init__.py
rip_counter/captcha_solver/captchanet_solver.py
rip_counter/captcha_solver/manual_solver.py
rip_counter/utils/__init__.py
rip_counter/utils/archive.py
rip_counter/utils/download.py
rip_counter/utils/system.py
rip_counter/utils/windows.py