Metadata-Version: 2.1
Name: rip-counter
Version: 0.2.0
Summary: A vote counter for french RIP.
Home-page: https://github.com/hadim/rip-counter/
Author: Hadrien Mary
Author-email: hadrien.mary@gmail.com
License: UNKNOWN
Platform: UNKNOWN
Classifier: Development Status :: 5 - Production/Stable
Classifier: Intended Audience :: Developers
Classifier: Natural Language :: English
Classifier: License :: OSI Approved :: BSD License
Classifier: Operating System :: OS Independent
Classifier: Programming Language :: Python
Classifier: Programming Language :: Python :: 3
